LICENSE
MANIFEST.in
README.rst
setup.py
django_waffle_session.egg-info/PKG-INFO
django_waffle_session.egg-info/SOURCES.txt
django_waffle_session.egg-info/dependency_links.txt
django_waffle_session.egg-info/not-zip-safe
django_waffle_session.egg-info/pbr.json
django_waffle_session.egg-info/top_level.txt
waffle/__init__.py
waffle/admin.py
waffle/compat.py
waffle/decorators.py
waffle/helpers.py
waffle/middleware.py
waffle/models.py
waffle/settings.py
waffle/urls.py
waffle/views.py
waffle/management/__init__.py
waffle/management/commands/__init__.py
waffle/management/commands/flag.py
waffle/management/commands/sample.py
waffle/management/commands/switch.py
waffle/migrations/0001_initial.py
waffle/migrations/0002_flag_sessions.py
waffle/migrations/0003_verifieduser.py
waffle/migrations/0004_remove_flag_sessions.py
waffle/migrations/__init__.py
waffle/south_migrations/0001_initial.py
waffle/south_migrations/0002_auto__add_sample.py
waffle/south_migrations/0003_auto__add_field_flag_note__add_field_switch_note__add_field_sample_not.py
waffle/south_migrations/0004_auto__add_field_flag_testing.py
waffle/south_migrations/0005_auto__add_field_flag_created__add_field_flag_modified.py
waffle/south_migrations/0006_auto__add_field_switch_created__add_field_switch_modified__add_field_s.py
waffle/south_migrations/0007_auto__chg_field_flag_created__chg_field_flag_modified__chg_field_switc.py
waffle/south_migrations/0008_auto__add_field_flag_languages.py
waffle/south_migrations/0009_auto__add_field_flag_sessions.py
waffle/south_migrations/0010_auto__add_verifieduser.py
waffle/south_migrations/0011_auto__del_field_flag_sessions.py
waffle/south_migrations/__init__.py
waffle/templates/waffle/waffle.js
waffle/templatetags/__init__.py
waffle/templatetags/waffle_tags.py
waffle/tests/__init__.py
waffle/tests/base.py
waffle/tests/test_decorators.py
waffle/tests/test_middleware.py
waffle/tests/test_templates.py
waffle/tests/test_views.py
waffle/tests/test_waffle.py